mpl_toolkits.clifford-0.0.3-py3.8-nspkg.pth
mpl_toolkits/clifford/__init__.py
mpl_toolkits/clifford/_version.py
mpl_toolkits.clifford-0.0.3.dist-info/LICENSE.txt
mpl_toolkits.clifford-0.0.3.dist-info/METADATA
mpl_toolkits.clifford-0.0.3.dist-info/WHEEL
mpl_toolkits.clifford-0.0.3.dist-info/namespace_packages.txt
mpl_toolkits.clifford-0.0.3.dist-info/top_level.txt
mpl_toolkits.clifford-0.0.3.dist-info/RECORD
