Metadata-Version: 2.1
Name: mpl-toolkits.clifford
Version: 0.0.3
Summary: Matplotlib tools for clifford
Home-page: UNKNOWN
Author: Eric Wieser
License: MIT
Project-URL: Bug Tracker, https://github.com/pygae/mpl_toolkits.clifford/issues
Project-URL: Source Code, https://github.com/pygae/mpl_toolkits.clifford
Platform: UNKNOWN
Classifier: Intended Audience :: Science/Research
Classifier: Topic :: Scientific/Engineering :: Mathematics
Classifier: License :: OSI Approved :: MIT License
Classifier: Programming Language :: Python :: 3
Classifier: Programming Language :: Python :: 3.5
Classifier: Programming Language :: Python :: 3.6
Classifier: Programming Language :: Python :: 3.7
Requires-Python: >=3.5
